{"entities":[],"blocks":[{"x":0,"y":5,"id":"GrassBlock","tags":{"block":true}},{"x":1,"y":5,"id":"GrassBlock","tags":{"block":true}},{"x":2,"y":5,"id":"GrassBlock","tags":{"block":true}},{"x":3,"y":5,"id":"GrassBlock","tags":{"block":true}},{"x":4,"y":5,"id":"GrassBlock","tags":{"block":true}},{"x":5,"y":5,"id":"GrassBlock","tags":{"block":true}},{"x":5,"y":6,"id":"GroundBlock","tags":{"block":true}},{"x":6,"y":5,"id":"GrassBlock","tags":{"block":true}},{"x":6,"y":6,"id":"GroundBlock","tags":{"block":true}},{"x":7,"y":5,"id":"GrassBlock","tags":{"block":true}},{"x":7,"y":6,"id":"GroundBlock","tags":{"block":true}},{"x":8,"y":5,"id":"GrassBlock","tags":{"block":true}},{"x":8,"y":6,"id":"GroundBlock","tags":{"block":true}},{"x":9,"y":5,"id":"GrassBlock","tags":{"block":true}},{"x":9,"y":6,"id":"GroundBlock","tags":{"block":true}},{"x":10,"y":5,"id":"GrassBlock","tags":{"block":true}},{"x":10,"y":6,"id":"GroundBlock","tags":{"block":true}},{"x":11,"y":5,"id":"GrassBlock","tags":{"block":true}},{"x":11,"y":6,"id":"GroundBlock","tags":{"block":true}},{"x":12,"y":5,"id":"GrassBlock","tags":{"block":true}},{"x":13,"y":5,"id":"GrassBlock","tags":{"block":true}},{"x":14,"y":5,"id":"GrassBlock","tags":{"block":true}},{"x":15,"y":5,"id":"GrassBlock","tags":{"block":true}},{"x":16,"y":5,"id":"GrassBlock","tags":{"block":true}},{"x":17,"y":5,"id":"GrassBlock","tags":{"block":true}},{"x":18,"y":5,"id":"GrassBlock","tags":{"block":true}},{"x":19,"y":5,"id":"GrassBlock","tags":{"block":true}},{"x":20,"y":5,"id":"GrassBlock","tags":{"block":true}},{"x":21,"y":5,"id":"GrassBlock","tags":{"block":true}},{"x":22,"y":5,"id":"GrassBlock","tags":{"block":true}},{"x":23,"y":5,"id":"GrassBlock","tags":{"block":true}},{"x":24,"y":5,"id":"GrassBlock","tags":{"block":true}},{"x":25,"y":5,"id":"GrassBlock","tags":{"block":true}},{"x":26,"y":5,"id":"GrassBlock","tags":{"block":true}},{"x":27,"y":5,"id":"GrassBlock","tags":{"block":true}},{"x":28,"y":5,"id":"GrassBlock","tags":{"block":true}},{"x":29,"y":5,"id":"GrassBlock","tags":{"block":true}},{"x":30,"y":5,"id":"GrassBlock","tags":{"block":true}},{"x":31,"y":5,"id":"GrassBlock","tags":{"block":true}},{"x":32,"y":5,"id":"GrassBlock","tags":{"block":true}},{"x":33,"y":5,"id":"GrassBlock","tags":{"block":true}},{"x":34,"y":5,"id":"GrassBlock","tags":{"block":true}},{"x":35,"y":5,"id":"GrassBlock","tags":{"block":true}},{"x":36,"y":5,"id":"GrassBlock","tags":{"block":true}},{"x":37,"y":5,"id":"GrassBlock","tags":{"block":true}},{"x":38,"y":5,"id":"GrassBlock","tags":{"block":true}},{"x":39,"y":5,"id":"GrassBlock","tags":{"block":true}},{"x":40,"y":5,"id":"GrassBlock","tags":{"block":true}},{"x":41,"y":5,"id":"GrassBlock","tags":{"block":true}},{"x":42,"y":5,"id":"GrassBlock","tags":{"block":true}},{"x":43,"y":5,"id":"GrassBlock","tags":{"block":true}},{"x":44,"y":5,"id":"GrassBlock","tags":{"block":true}},{"x":45,"y":5,"id":"GrassBlock","tags":{"block":true}},{"x":46,"y":5,"id":"GrassBlock","tags":{"block":true}},{"x":47,"y":5,"id":"GrassBlock","tags":{"block":true}},{"x":48,"y":5,"id":"GrassBlock","tags":{"block":true}},{"x":49,"y":5,"id":"GrassBlock","tags":{"block":true}},{"x":50,"y":5,"id":"GrassBlock","tags":{"block":true}},{"x":51,"y":5,"id":"GrassBlock","tags":{"block":true}},{"x":52,"y":5,"id":"GrassBlock","tags":{"block":true}},{"x":53,"y":5,"id":"GrassBlock","tags":{"block":true}},{"x":54,"y":5,"id":"GrassBlock","tags":{"block":true}},{"x":55,"y":5,"id":"GrassBlock","tags":{"block":true}},{"x":56,"y":5,"id":"GrassBlock","tags":{"block":true}},{"x":57,"y":5,"id":"GrassBlock","tags":{"block":true}},{"x":58,"y":5,"id":"GrassBlock","tags":{"block":true}},{"x":59,"y":5,"id":"GrassBlock","tags":{"block":true}}],"background":"<DEFAULT>","width":60,"height":30}